gempaterkini/__init__.py
Earthquakedetection-0.0.5.dist-info/LICENSE
Earthquakedetection-0.0.5.dist-info/METADATA
Earthquakedetection-0.0.5.dist-info/WHEEL
Earthquakedetection-0.0.5.dist-info/top_level.txt
Earthquakedetection-0.0.5.dist-info/RECORD
