Metadata-Version: 2.1
Name: Earthquakedetection
Version: 0.0.5
Summary: This package will detect the latest earthquakes from BMKG (Meteorology, Climatology, and Geophysical Agency)
Home-page: https://github.com/wahyukmr/Earthquake-detection
Author: wahyukmr
Author-email: maryu9292@gmail.com
License: UNKNOWN
Project-URL: Bug Tracker, https://github.com/pypa/sampleproject/issues
Platform: UNKNOWN
Classifier: Programming Language :: Python :: 3
Classifier: License :: OSI Approved :: GNU General Public License v3 (GPLv3)
Classifier: Operating System :: OS Independent
Classifier: Framework :: Scrapy
Classifier: Development Status :: 5 - Production/Stable
Requires-Python: >=3.6
License-File: LICENSE
